sklmer/__init__.py
sklmer/_estimators.py
sklmer/_version.py
sklmer/tests/__init__.py
sklmer/tests/test_common.py
sklmer/tests/test_estimators.py
sklearn_lmer-0.0.5.dist-info/LICENSE
sklearn_lmer-0.0.5.dist-info/METADATA
sklearn_lmer-0.0.5.dist-info/WHEEL
sklearn_lmer-0.0.5.dist-info/top_level.txt
sklearn_lmer-0.0.5.dist-info/RECORD
