Metadata-Version: 2.1
Name: sklearn-lmer
Version: 0.0.5
Summary: Scikit-learn estimator wrappers for pymer4 wrapped LME4 mixed effects models
Home-page: https://github.com/nimh-mbdu/sklearn-lmer
Maintainer: D. Nielson
Maintainer-email: dylan.nielson@gmail.com
License: CC0
Download-URL: https://github.com/nimh-mbdu/sklearn-lmer
Platform: UNKNOWN
Classifier: Intended Audience :: Science/Research
Classifier: License :: CC0 1.0 Universal (CC0 1.0) Public Domain Dedication
Classifier: Programming Language :: Python
Classifier: Topic :: Scientific/Engineering
Classifier: Operating System :: POSIX
Classifier: Operating System :: Unix
Classifier: Operating System :: MacOS
Classifier: Programming Language :: Python :: 3.7
Requires-Dist: numpy
Requires-Dist: scipy
Requires-Dist: scikit-learn
Requires-Dist: pandas
Requires-Dist: pymer4
Provides-Extra: docs
Requires-Dist: sphinx ; extra == 'docs'
Requires-Dist: sphinx-gallery ; extra == 'docs'
Requires-Dist: sphinx-rtd-theme ; extra == 'docs'
Requires-Dist: numpydoc ; extra == 'docs'
Requires-Dist: matplotlib ; extra == 'docs'
Provides-Extra: tests
Requires-Dist: pytest ; extra == 'tests'
Requires-Dist: pytest-cov ; extra == 'tests'
